aerolattice-0.11.0.dist-info/METADATA
aerolattice-0.11.0.dist-info/WHEEL
aerolattice-0.11.0.dist-info/licenses/LICENSE
aerolattice/__init__.py
aerolattice/aerolattice.cpython-312-x86_64-linux-gnu.so
aerolattice-0.11.0.dist-info/RECORD
