Metadata-Version: 2.4
Name: aerolattice
Version: 0.11.0
Classifier: Programming Language :: Rust
Classifier: Programming Language :: Python :: Implementation :: CPython
Classifier: Programming Language :: Python :: Implementation :: PyPy
License-File: LICENSE
Summary: A blazingly fast aerodynamics package built for modern aerospace applications.
License: MIT
Requires-Python: >=3.8
Project-URL: Source Code, https://github.com/josephrhobbs/aerolattice.git
